moustique/__init__.py
moustique/client.py
moustique_client-0.1.1.dist-info/METADATA
moustique_client-0.1.1.dist-info/WHEEL
moustique_client-0.1.1.dist-info/top_level.txt
moustique_client-0.1.1.dist-info/RECORD
