Metadata-Version: 2.1
Name: moustique-client
Version: 0.1.1
Summary: Python client for Moustique messaging server
Home-page: https://github.com/moustiqueserver/moustique
Author: Moustique
Author-email: mulf@protonmail.com
Project-URL: Bug Reports, https://github.com/moustiqueserver/moustique/issues
Project-URL: Source, https://github.com/moustiqueserver/moustique
Project-URL: Documentation, https://github.com/moustiqueserver/moustique#readme
Keywords: moustique pubsub messaging realtime
Classifier: Development Status :: 4 - Beta
Classifier: Intended Audience :: Developers
Classifier: Topic :: Software Development :: Libraries :: Python Modules
Classifier: Topic :: System :: Networking
Classifier: Programming Language :: Python :: 3
Classifier: Programming Language :: Python :: 3.7
Classifier: Programming Language :: Python :: 3.8
Classifier: Programming Language :: Python :: 3.9
Classifier: Programming Language :: Python :: 3.10
Classifier: Programming Language :: Python :: 3.11
Classifier: License :: OSI Approved :: GNU General Public License v3 (GPLv3)
Classifier: Operating System :: OS Independent
Requires-Python: >=3.7
Requires-Dist: requests >=2.25.0
